EasyGram/__init__.py
EasyGram/exception.py
EasyGram/state.py
EasyGram/types.py
EasyGram/utils.py
EasyGram/Async/__init__.py
EasyGram/Async/types.py
EasyGram/imitation/__init__.py
easygram-0.0.4.2.dist-info/METADATA
easygram-0.0.4.2.dist-info/WHEEL
easygram-0.0.4.2.dist-info/top_level.txt
easygram-0.0.4.2.dist-info/RECORD
