Metadata-Version: 2.4
Name: EasyGram
Version: 0.0.4.2
Summary: Библиотека для удобного и многофункционального(в будущем) использования.
Home-page: https://github.com/flexyyyapk/EasyGram/
Author: flexyyy
Classifier: Programming Language :: Python :: 3
Classifier: License :: OSI Approved :: MIT License
Classifier: Operating System :: OS Independent
Requires-Python: >=3.7
Requires-Dist: aiohttp
Dynamic: author
Dynamic: classifier
Dynamic: description
Dynamic: description-content-type
Dynamic: home-page
Dynamic: requires-dist
Dynamic: requires-python
Dynamic: summary
